<?xml version="1.0" encoding="UTF-8" ?>
<class name="OpenTelemetryScope" inherits="Resource" xmlns:xsi="http://www.w3.org/2001/XMLSchema-instance" xsi:noNamespaceSchemaLocation="../../../doc/class.xsd">
	<brief_description>
	</brief_description>
	<description>
	</description>
	<tutorials>
	</tutorials>
	<methods>
		<method name="add_attribute">
			<return type="void" />
			<param index="0" name="key" type="String" />
			<param index="1" name="value" type="Variant" />
			<description>
			</description>
		</method>
		<method name="to_otlp_dict" qualifiers="const">
			<return type="Dictionary" />
			<description>
			</description>
		</method>
	</methods>
	<members>
		<member name="attributes" type="Dictionary" setter="set_attributes" getter="get_attributes" default="{}">
		</member>
		<member name="version" type="String" setter="set_version" getter="get_version" default="&quot;&quot;">
		</member>
	</members>
</class>
