<?xml version="1.0" encoding="UTF-8" ?>
<class name="SlicedMesh" inherits="Resource" xmlns:xsi="http://www.w3.org/2001/XMLSchema-instance" xsi:noNamespaceSchemaLocation="../../../doc/class.xsd">
	<brief_description>
		Holds the result of a Slicer cut
	</brief_description>
	<description>
	</description>
	<tutorials>
	</tutorials>
	<members>
		<member name="lower_mesh" type="Mesh" setter="set_lower_mesh" getter="get_lower_mesh">
		</member>
		<member name="upper_mesh" type="Mesh" setter="set_upper_mesh" getter="get_upper_mesh">
		</member>
	</members>
</class>
